LICENSE.txt
MANIFEST.in
README.md
pyproject.toml
requirements.txt
setup.py
quinteng/VERSION.txt
quinteng/__init__.py
quinteng/exceptions.py
quinteng/execute_function.py
quinteng/user_config.py
quinteng/util.py
quinteng/version.py
quinteng/algorithms/__init__.py
quinteng/algorithms/algorithm_result.py
quinteng/algorithms/exceptions.py
quinteng/algorithms/variational_algorithm.py
quinteng/algorithms/amplitude_amplifiers/__init__.py
quinteng/algorithms/amplitude_amplifiers/amplification_problem.py
quinteng/algorithms/amplitude_amplifiers/amplitude_amplifier.py
quinteng/algorithms/amplitude_amplifiers/grover.py
quinteng/algorithms/amplitude_estimators/__init__.py
quinteng/algorithms/amplitude_estimators/ae.py
quinteng/algorithms/amplitude_estimators/ae_utils.py
quinteng/algorithms/amplitude_estimators/amplitude_estimator.py
quinteng/algorithms/amplitude_estimators/estimation_problem.py
quinteng/algorithms/amplitude_estimators/fae.py
quinteng/algorithms/amplitude_estimators/iae.py
quinteng/algorithms/amplitude_estimators/mlae.py
quinteng/algorithms/eigen_solvers/__init__.py
quinteng/algorithms/eigen_solvers/eigen_solver.py
quinteng/algorithms/eigen_solvers/numpy_eigen_solver.py
quinteng/algorithms/factorizers/__init__.py
quinteng/algorithms/factorizers/shor.py
quinteng/algorithms/linear_solvers/__init__.py
quinteng/algorithms/linear_solvers/hhl.py
quinteng/algorithms/linear_solvers/linear_solver.py
quinteng/algorithms/linear_solvers/numpy_linear_solver.py
quinteng/algorithms/linear_solvers/matrices/__init__.py
quinteng/algorithms/linear_solvers/matrices/linear_system_matrix.py
quinteng/algorithms/linear_solvers/matrices/numpy_matrix.py
quinteng/algorithms/linear_solvers/matrices/tridiagonal_toeplitz.py
quinteng/algorithms/linear_solvers/observables/__init__.py
quinteng/algorithms/linear_solvers/observables/absolute_average.py
quinteng/algorithms/linear_solvers/observables/linear_system_observable.py
quinteng/algorithms/linear_solvers/observables/matrix_functional.py
quinteng_chaoyue.egg-info/PKG-INFO
quinteng_chaoyue.egg-info/SOURCES.txt
quinteng_chaoyue.egg-info/dependency_links.txt
quinteng_chaoyue.egg-info/entry_points.txt
quinteng_chaoyue.egg-info/not-zip-safe
quinteng_chaoyue.egg-info/requires.txt
quinteng_chaoyue.egg-info/top_level.txt
