Metadata-Version: 2.1
Name: quinteng-chaoyue
Version: 1.0.0
Summary: Software for developing quantum computing programs
Home-page: https://github.com/Quinteng/quinteng-chaoyue
Author: Quinteng Development Team
Author-email: hello@quinteng.org
License: Apache 2.0
Project-URL: Bug Tracker, https://github.com/Quinteng/quinteng-chaoyue/issues
Project-URL: Documentation, https://quinteng.org/documentation/
Project-URL: Source Code, https://github.com/Quinteng/quinteng-chaoyue
Keywords: quinteng sdk quantum
Platform: UNKNOWN
Classifier: Environment :: Console
Classifier: License :: OSI Approved :: Apache Software License
Classifier: Intended Audience :: Developers
Classifier: Intended Audience :: Science/Research
Classifier: Operating System :: Microsoft :: Windows
Classifier: Operating System :: MacOS
Classifier: Operating System :: POSIX :: Linux
Classifier: Programming Language :: Python :: 3 :: Only
Classifier: Programming Language :: Python :: 3.7
Classifier: Programming Language :: Python :: 3.8
Classifier: Programming Language :: Python :: 3.9
Classifier: Topic :: Scientific/Engineering
Requires-Python: >=3.7
Provides-Extra: visualization
Provides-Extra: bip-mapper
Provides-Extra: crosstalk-pass
Provides-Extra: all
License-File: LICENSE.txt
